Metadata-Version: 2.1
Name: fragile_gym_super_mario_bros
Version: 7.4.1
Summary: Super Mario Bros. for OpenAI Gym
Author-email: "Guillem Duran (fork)" <info@fragile.tech>, "Christian Kauten (original)" <kautencreations@gmail.com>
License: Proprietary
Project-URL: Homepage, https://github.com/Kautenja/gym-super-mario-bros
Keywords: OpenAI-Gym,NES,Super-Mario-Bros,Lost-Levels,Reinforcement-Learning-Environment
Classifier: Development Status :: 5 - Production/Stable
Classifier: Intended Audience :: Developers
Classifier: Intended Audience :: Science/Research
Classifier: License :: Free For Educational Use
Classifier: Operating System :: MacOS :: MacOS X
Classifier: Operating System :: POSIX :: Linux
Classifier: Operating System :: Microsoft :: Windows
Classifier: Programming Language :: Python :: 3 :: Only
Classifier: Programming Language :: Python :: 3.5
Classifier: Programming Language :: Python :: 3.6
Classifier: Programming Language :: Python :: 3.7
Classifier: Programming Language :: Python :: 3.8
Classifier: Programming Language :: Python :: 3.9
Classifier: Programming Language :: Python :: 3.10
Classifier: Programming Language :: Python :: 3.11
Classifier: Topic :: Games/Entertainment :: Side-Scrolling/Arcade Games
Classifier: Topic :: Scientific/Engineering :: Artificial Intelligence
License-File: LICENSE
Provides-Extra: dev
Requires-Dist: fragile-nes-py; extra == "dev"
